src/__init__.py
src/hdj.py
src/hdj_fileio.py
src/hdj_linkchecker.py
src/hdj_util.py
tests/__init__.py
tests/test_hdj_fileio.py
tests/test_hdj_linkchecker.py
He_s_Dead_Jim-1.0.5.dist-info/METADATA
He_s_Dead_Jim-1.0.5.dist-info/WHEEL
He_s_Dead_Jim-1.0.5.dist-info/entry_points.txt
He_s_Dead_Jim-1.0.5.dist-info/top_level.txt
He_s_Dead_Jim-1.0.5.dist-info/RECORD
