Metadata-Version: 2.1
Name: He-s-Dead-Jim
Version: 1.0.5
Summary: A command-line tool for finding and reporting dead/broken links in a file or webpage.
Home-page: https://github.com/chrispinkney/He-s-Dead-Jim
Author: Chris Pinkney
Author-email: hey@chrispinkney.com
License: MIT
Platform: UNKNOWN
Classifier: Programming Language :: Python :: 3
Classifier: License :: OSI Approved :: MIT License
Classifier: Operating System :: OS Independent
Requires-Python: >=3.6
Requires-Dist: argparse (==1.4.0)
Requires-Dist: requests (==2.24.0)
Requires-Dist: beautifulsoup4 (==4.9.1)
Requires-Dist: datetime (==4.3)
Requires-Dist: colorama (==0.4.4)
Requires-Dist: black (==20.8b1)
Requires-Dist: flake8 (==3.8.4)
Requires-Dist: pre-commit (==2.7.1)
Requires-Dist: pytest (==6.1.2)
Requires-Dist: pytest-cov (==2.10.1)
